clara/__init__.py
clara/adapters/__init__.py
clara/adapters/config.py
clara/adapters/exceptions.py
clara/adapters/loader.py
clara/adapters/registry.py
clara/cli/__init__.py
clara/cli/main.py
clara/cli/commands/__init__.py
clara/cli/commands/adapters.py
clara/cli/commands/eval.py
clara/cli/commands/infer.py
clara/config/__init__.py
clara/config/loader.py
clara/config/templates/__init__.py
clara/config/templates/default.yaml
clara/config/templates/finetune.yaml
clara/config/templates/multi_adapter.yaml
clara/config/templates/test_train.yaml
clara/data/__init__.py
clara/data/collator.py
clara/data/dataset.py
clara/engine/__init__.py
clara/engine/batch.py
clara/engine/factory.py
clara/engine/gguf.py
clara/engine/inference.py
clara/eval/__init__.py
clara/eval/arc.py
clara/eval/harness.py
clara/eval/hellaswag.py
clara/eval/perplexity.py
clara/eval/results.py
clara/models/__init__.py
clara/models/exceptions.py
clara/models/loader.py
clara/server/__init__.py
clara/server/app.py
clara/tokenizer/__init__.py
clara/tokenizer/wrapper.py
clara/training/__init__.py
clara/training/callbacks.py
clara/training/config.py
clara/training/trainer.py
clara/utils/__init__.py
clara/utils/checksums.py
clara/utils/device.py
clara/utils/errors.py
clara/utils/logging.py
clara/utils/memory.py
ml_clara-1.5.0.dist-info/licenses/LICENSE
ml_clara-1.5.0.dist-info/METADATA
ml_clara-1.5.0.dist-info/WHEEL
ml_clara-1.5.0.dist-info/entry_points.txt
ml_clara-1.5.0.dist-info/top_level.txt
ml_clara-1.5.0.dist-info/RECORD
